Metadata-Version: 2.4
Name: PROCS_Promotion_Tool
Version: 0.1.5
Summary: Automated Excel & SQL Promotion Data Flow
Author: surapatsue
Author-email: NAKARINSUE@outlook.com
Requires-Python: >=3.9
License-File: LICENSE
Requires-Dist: SQLAlchemy==2.0.41
Requires-Dist: pyodbc==5.2.0
Requires-Dist: openpyxl==3.1.5
Requires-Dist: pandas==2.3.0
Requires-Dist: python-dotenv==1.1.1
Requires-Dist: python-barcode==0.15.1
Requires-Dist: pillow==11.3.0
Requires-Dist: barcode
Requires-Dist: watchdog==4.0.0
Requires-Dist: pyinstaller==6.16.0
Requires-Dist: requests==2.32.4
Requires-Dist: tqdm==4.66.4
Requires-Dist: icecream==2.1.8
Requires-Dist: matplotlib==3.10.7
Requires-Dist: PyQt6==6.10.0
Dynamic: author
Dynamic: author-email
Dynamic: license-file
Dynamic: requires-dist
Dynamic: requires-python
Dynamic: summary
